json_sample_generator/DefaultValueGenerator.py
json_sample_generator/JSONSchemaGenerator.py
json_sample_generator/SchemaGeneratorBuilder.py
json_sample_generator/__init__.py
json_sample_generator/py.typed
json_sample_generator/helpers/__init__.py
json_sample_generator/helpers/allof_handler.py
json_sample_generator/helpers/utils.py
json_sample_generator/models/__init__.py
json_sample_generator/models/models.py
sample_generator-0.1.0.dist-info/METADATA
sample_generator-0.1.0.dist-info/WHEEL
sample_generator-0.1.0.dist-info/licenses/LICENSE
sample_generator-0.1.0.dist-info/RECORD
