Metadata-Version: 2.4
Name: sample_generator
Version: 0.1.0
Summary: Generate sample data from JSON schema or OAS models
Project-URL: Homepage, https://github.com/bartoszm/sample_generator
Project-URL: Repository, https://github.com/bartoszm/sample_generator
Project-URL: Issues, https://github.com/bartoszm/sample_generator/issues
Project-URL: Documentation, https://github.com/bartoszm/sample_generator#readme
Author-email: Bartosz Michalik <bartosz.michalik@gmail.com>
License: MIT
License-File: LICENSE
Keywords: fixtures,generator,json,jsonschema,oas,openapi,testing
Classifier: Development Status :: 3 - Alpha
Classifier: Intended Audience :: Developers
Classifier: License :: OSI Approved :: MIT License
Classifier: Operating System :: OS Independent
Classifier: Programming Language :: Python :: 3
Classifier: Programming Language :: Python :: 3 :: Only
Classifier: Programming Language :: Python :: 3.12
Classifier: Programming Language :: Python :: 3.13
Classifier: Topic :: Software Development :: Testing
Classifier: Typing :: Typed
Requires-Python: >=3.12
Requires-Dist: faker==37.1.0
Requires-Dist: jsonref~=1.1
Requires-Dist: jsonschema~=4.23
Requires-Dist: pydantic==2.11.3
Requires-Dist: pyyaml~=6.0
Requires-Dist: rstr==3.2.2
Provides-Extra: dev
Requires-Dist: black>=24.4; extra == 'dev'
Requires-Dist: ipykernel>=6.29; extra == 'dev'
Requires-Dist: isort>=5.13; extra == 'dev'
Requires-Dist: mypy>=1.10; extra == 'dev'
Requires-Dist: pre-commit>=3.7; extra == 'dev'
Requires-Dist: pytest>=8.3; extra == 'dev'
Requires-Dist: ruff>=0.5; extra == 'dev'
